<?xml version="1.0" encoding="iso-8859-1"?>
<RECIPES>
  <RECIPE>
    <VERSION>1</VERSION>
    <TYPE>All Grain</TYPE>
    <BREWER>mountainman</BREWER>
    <BATCH_SIZE>11.36</BATCH_SIZE>
    <DISPLAY_BATCH_SIZE>11.36 L</DISPLAY_BATCH_SIZE>
    <BOIL_SIZE>15.33</BOIL_SIZE>
    <DISPLAY_BOIL_SIZE>15.33 L</DISPLAY_BOIL_SIZE>
    <BOIL_TIME>90</BOIL_TIME>
    <EFFICIENCY>78</EFFICIENCY>
    <TASTE_NOTES>2016 NHC Final Round Gold Medal-Winning Saison Recipe</TASTE_NOTES>
    <DATE>6/22/2016 3:24:09 PM</DATE>
    <OG>1.0571</OG>
    <EST_OG>1.0571</EST_OG>
    <FG>1.0017</FG>
    <EST_FG>1.0017</EST_FG>
    <IBU>40</IBU>
    <COLOR>4</COLOR>
    <EST_COLOR>4</EST_COLOR>
    <ABV>7.4</ABV>
    <EST_ABV>7.4</EST_ABV>
    <PRIMARY_AGE>14400</PRIMARY_AGE>
    <PRIMARY_TEMP>18</PRIMARY_TEMP>
    <SECONDARY_AGE>0</SECONDARY_AGE>
    <SECONDARY_TEMP>7</SECONDARY_TEMP>
    <FERMENTATION_STAGES>2</FERMENTATION_STAGES>
    <STYLE>
      <CATEGORY_NUMBER>16</CATEGORY_NUMBER>
      <STYLE_LETTER>C</STYLE_LETTER>
      <NAME>Saison</NAME>
      <VERSION>1</VERSION>
      <STYLE_GUIDE>BJCP 2008</STYLE_GUIDE>
      <OG_MIN>1.048</OG_MIN>
      <OG_MAX>1.065</OG_MAX>
      <FG_MIN>1.002</FG_MIN>
      <FG_MAX>1.012</FG_MAX>
      <IBU_MIN>20</IBU_MIN>
      <IBU_MAX>35</IBU_MAX>
      <COLOR_MIN>5</COLOR_MIN>
      <COLOR_MAX>14</COLOR_MAX>
    </STYLE>
    <EQUIPMENT>
      <NAME>PicoBrew Z/Zymatic</NAME>
      <VERSION>1</VERSION>
    </EQUIPMENT>
    <NOTES>This beer took 1st place at the Final Round of 2016 NHC for Category 19 - Belgian and French Ale.

Mashed at 148 for 60 minutes and 154 for 30 minutes. Originally whirlpooled 1oz of Styrian Goldings and 0.5oz Czech Saaz for 10 minutes at 185, but this recipe has been adjusted to a 10 minute addition in the boil with the Goldings and Saaz in Adjunct Compartments 2 and 3. Whirlfloc and yeast nutrient added with 10 minutes left in boil. Pitched starter of WY3711 at ~70F, and let the yeast free rise to 77 over 4 days and held at 77F for 7 days before cold crashing to 34F. FG at 1.002. Bottle conditioned to 3 volumes of CO2.</NOTES>
    <ZYMATIC>
      <MASH_TEMP>63</MASH_TEMP>
      <MASH_TIME>120</MASH_TIME>
      <BOIL_TEMP>97</BOIL_TEMP>
      <STEP>
        <NAME>Heat to Dough In</NAME>
        <TEMP>39</TEMP>
        <TIME>0</TIME>
        <LOCATION>PassThrough</LOCATION>
        <DRAIN>0</DRAIN>
      </STEP>
      <STEP>
        <NAME>Dough In</NAME>
        <TEMP>39</TEMP>
        <TIME>20</TIME>
        <LOCATION>Mash</LOCATION>
        <DRAIN>8</DRAIN>
      </STEP>
      <STEP>
        <NAME>Heat to Mash 1</NAME>
        <TEMP>67</TEMP>
        <TIME>0</TIME>
        <LOCATION>PassThrough</LOCATION>
        <DRAIN>0</DRAIN>
      </STEP>
      <STEP>
        <NAME>Mash 1</NAME>
        <TEMP>67</TEMP>
        <TIME>30</TIME>
        <LOCATION>Mash</LOCATION>
        <DRAIN>8</DRAIN>
      </STEP>
      <STEP>
        <NAME>Heat to Mash 2</NAME>
        <TEMP>68</TEMP>
        <TIME>0</TIME>
        <LOCATION>PassThrough</LOCATION>
        <DRAIN>0</DRAIN>
      </STEP>
      <STEP>
        <NAME>Mash 2</NAME>
        <TEMP>68</TEMP>
        <TIME>60</TIME>
        <LOCATION>Mash</LOCATION>
        <DRAIN>8</DRAIN>
      </STEP>
      <STEP>
        <NAME>Heat to Mash Out</NAME>
        <TEMP>79</TEMP>
        <TIME>0</TIME>
        <LOCATION>PassThrough</LOCATION>
        <DRAIN>0</DRAIN>
      </STEP>
      <STEP>
        <NAME>Mash Out</NAME>
        <TEMP>79</TEMP>
        <TIME>10</TIME>
        <LOCATION>Mash</LOCATION>
        <DRAIN>8</DRAIN>
      </STEP>
      <STEP>
        <NAME>Heat to Boil</NAME>
        <TEMP>97</TEMP>
        <TIME>0</TIME>
        <LOCATION>PassThrough</LOCATION>
        <DRAIN>0</DRAIN>
      </STEP>
      <STEP>
        <NAME>Boil Adjunct 1</NAME>
        <TEMP>97</TEMP>
        <TIME>75</TIME>
        <LOCATION>Adjunct1</LOCATION>
        <DRAIN>0</DRAIN>
      </STEP>
      <STEP>
        <NAME>Boil Adjunct 2</NAME>
        <TEMP>97</TEMP>
        <TIME>5</TIME>
        <LOCATION>Adjunct2</LOCATION>
        <DRAIN>0</DRAIN>
      </STEP>
      <STEP>
        <NAME>Boil Adjunct 3</NAME>
        <TEMP>97</TEMP>
        <TIME>10</TIME>
        <LOCATION>Adjunct3</LOCATION>
        <DRAIN>5</DRAIN>
      </STEP>
      <STEP>
        <NAME>Connect Chiller</NAME>
        <TEMP>18</TEMP>
        <TIME>0</TIME>
        <LOCATION>Pause</LOCATION>
        <DRAIN>0</DRAIN>
      </STEP>
      <STEP>
        <NAME>Chill</NAME>
        <TEMP>18</TEMP>
        <TIME>10</TIME>
        <LOCATION>PassThrough</LOCATION>
        <DRAIN>10</DRAIN>
      </STEP>
    </ZYMATIC>
    <MASH>
      <NAME>MultiStep</NAME>
      <VERSION>1</VERSION>
      <GRAIN_TEMP>22.22222</GRAIN_TEMP>
      <MASH_STEPS>
        <MASH_STEP>
          <NAME>Dough In</NAME>
          <VERSION>1</VERSION>
          <TYPE>Temperature</TYPE>
          <STEP_TEMP>39</STEP_TEMP>
          <STEP_TIME>20</STEP_TIME>
        </MASH_STEP>
        <MASH_STEP>
          <NAME>Mash 1</NAME>
          <VERSION>1</VERSION>
          <TYPE>Temperature</TYPE>
          <STEP_TEMP>67</STEP_TEMP>
          <STEP_TIME>30</STEP_TIME>
        </MASH_STEP>
        <MASH_STEP>
          <NAME>Mash 2</NAME>
          <VERSION>1</VERSION>
          <TYPE>Temperature</TYPE>
          <STEP_TEMP>68</STEP_TEMP>
          <STEP_TIME>60</STEP_TIME>
        </MASH_STEP>
        <MASH_STEP>
          <NAME>Mash Out</NAME>
          <VERSION>1</VERSION>
          <TYPE>Temperature</TYPE>
          <STEP_TEMP>79</STEP_TEMP>
          <STEP_TIME>10</STEP_TIME>
        </MASH_STEP>
      </MASH_STEPS>
    </MASH>
    <HOPS>
      <HOP>
        <NAME>Magnum</NAME>
        <VERSION>1</VERSION>
        <ALPHA>12</ALPHA>
        <AMOUNT>0.012</AMOUNT>
        <USE>Boil</USE>
        <TIME>90</TIME>
      </HOP>
      <HOP>
        <NAME>Styrian Goldings</NAME>
        <VERSION>1</VERSION>
        <ALPHA>5.5</ALPHA>
        <AMOUNT>0.0283</AMOUNT>
        <USE>Boil</USE>
        <TIME>10</TIME>
      </HOP>
      <HOP>
        <NAME>Saaz</NAME>
        <VERSION>1</VERSION>
        <ALPHA>3.5</ALPHA>
        <AMOUNT>0.0142</AMOUNT>
        <USE>Boil</USE>
        <TIME>10</TIME>
      </HOP>
    </HOPS>
    <WATERS>
      <WATER>
        <VERSION>1</VERSION>
        <AMOUNT>15.33</AMOUNT>
      </WATER>
    </WATERS>
    <FERMENTABLES>
      <FERMENTABLE>
        <NAME>Belgian Pils</NAME>
        <VERSION>1</VERSION>
        <AMOUNT>2.27</AMOUNT>
        <TYPE>Grain</TYPE>
        <YIELD>78.26</YIELD>
        <COLOR>1.5</COLOR>
      </FERMENTABLE>
      <FERMENTABLE>
        <NAME>Flaked Oats</NAME>
        <VERSION>1</VERSION>
        <AMOUNT>0.45</AMOUNT>
        <TYPE>Other Grain</TYPE>
        <YIELD>71.09</YIELD>
        <COLOR>2.2</COLOR>
      </FERMENTABLE>
      <FERMENTABLE>
        <NAME>Flaked Wheat</NAME>
        <VERSION>1</VERSION>
        <AMOUNT>0.45</AMOUNT>
        <TYPE>Other Grain</TYPE>
        <YIELD>73.91</YIELD>
        <COLOR>1.9</COLOR>
      </FERMENTABLE>
      <FERMENTABLE>
        <NAME>German Acid Malt</NAME>
        <VERSION>1</VERSION>
        <AMOUNT>0.13</AMOUNT>
        <TYPE>Grain</TYPE>
        <YIELD>73.04</YIELD>
        <COLOR>1.9</COLOR>
      </FERMENTABLE>
      <FERMENTABLE>
        <NAME>German Vienna</NAME>
        <VERSION>1</VERSION>
        <AMOUNT>0.12</AMOUNT>
        <TYPE>Grain</TYPE>
        <YIELD>78.26</YIELD>
        <COLOR>3.5</COLOR>
      </FERMENTABLE>
    </FERMENTABLES>
    <YEASTS>
      <YEAST>
        <NAME>French Saison</NAME>
        <VERSION>1</VERSION>
        <AMOUNT>0</AMOUNT>
        <FORM>Dry</FORM>
        <LABORATORY>Wyeast</LABORATORY>
        <PRODUCT_ID>3711</PRODUCT_ID>
        <MIN_TEMPERATURE>18</MIN_TEMPERATURE>
        <MAX_TEMPERATURE>25</MAX_TEMPERATURE>
        <ATTENUATION>97</ATTENUATION>
      </YEAST>
    </YEASTS>
    <MISCS>
      <MISC>
        <VERSION>1</VERSION>
        <NAME>Whirlfloc</NAME>
        <TYPE>Fining</TYPE>
        <AMOUNT>2.8</AMOUNT>
        <TIME>15</TIME>
        <USE>Boil</USE>
        <USE_FOR>Boil</USE_FOR>
        <NOTES>Amount in: </NOTES>
      </MISC>
      <MISC>
        <VERSION>1</VERSION>
        <NAME>Yeast Nutrient</NAME>
        <TYPE>Other</TYPE>
        <AMOUNT>2.8</AMOUNT>
        <TIME>15</TIME>
        <USE>Boil</USE>
        <USE_FOR>Boil</USE_FOR>
        <NOTES>Amount in: </NOTES>
      </MISC>
    </MISCS>
    <KEGSMART>
      <STEPS>
        <STEP>
          <NUMBER>1</NUMBER>
          <NAME>Fermentation</NAME>
          <TIME>14400</TIME>
          <TEMP>18</TEMP>
        </STEP>
        <STEP>
          <NUMBER>2</NUMBER>
          <NAME>Crash Chill</NAME>
          <TIME>0</TIME>
          <TEMP>7</TEMP>
        </STEP>
      </STEPS>
    </KEGSMART>
    <NAME>Oats n' Wheat Saison</NAME>
  </RECIPE>
</RECIPES>